motiflets/__init__.py
motiflets/competitors.py
motiflets/motiflets.py
motiflets/plotting.py
motiflets-0.4.1.dist-info/LICENSE
motiflets-0.4.1.dist-info/METADATA
motiflets-0.4.1.dist-info/WHEEL
motiflets-0.4.1.dist-info/top_level.txt
motiflets-0.4.1.dist-info/RECORD
