Metadata-Version: 2.1
Name: motiflets
Version: 0.4.1
Summary: Motiflets - Simple and Accurate Detection of Motifs in Time Series
Home-page: https://github.com/patrickzib/motiflets
Author: patrickzib
Author-email: patrickzib <void@void.com>
License: GNU GENERAL PUBLIC LICENSE
Project-URL: repository, https://github.com/patrickzib/motiflets
Keywords: machine-learning,time-series,motif-discovery,motif-sets,motif-pairs,unsupervised
Classifier: Intended Audience :: Science/Research
Classifier: Intended Audience :: Developers
Classifier: License :: OSI Approved :: BSD License
Classifier: Programming Language :: Python
Classifier: Topic :: Software Development
Classifier: Topic :: Scientific/Engineering
Classifier: Operating System :: Microsoft :: Windows
Classifier: Operating System :: POSIX
Classifier: Operating System :: Unix
Classifier: Operating System :: MacOS
Classifier: Programming Language :: Python :: 3.7
Classifier: Programming Language :: Python :: 3.8
Classifier: Programming Language :: Python :: 3.9
Classifier: Programming Language :: Python :: 3.10
Classifier: Programming Language :: Python :: 3.11
Classifier: Programming Language :: Python :: 3.12
Requires-Python: >=3.7
License-File: LICENSE
Requires-Dist: joblib >=1.1.0
Requires-Dist: numba >=0.55.1
Requires-Dist: numpy >=1.21.0
Requires-Dist: pandas >=1.1.0
Requires-Dist: scikit-learn >=0.24.0
Requires-Dist: scipy <2.0.0
Requires-Dist: seaborn >=0.11.2
Requires-Dist: tqdm >=4.63.0
Requires-Dist: matplotlib >=3.5.1
